<?xml version="1.0" encoding="UTF-8"?>
<!DOCTYPE generatorConfiguration
        PUBLIC "-//mybatis.org//DTD MyBatis Generator Configuration 1.0//EN"
        "http://mybatis.org/dtd/mybatis-generator-config_1_0.dtd">
<generatorConfiguration>
    <context id="MySqlTables"
                targetRuntime="MyBatis3Simple"
                defaultModelType="flat">
        <!--关键字与分隔符加反引号-->
        <property name="beginningDelimiter" value="`"/>
        <property name="endingDelimiter" value="`"/>
        <!--序列化以及字符串插件-->
        <plugin type="org.mybatis.generator.plugins.SerializablePlugin"/>
        <plugin type="org.mybatis.generator.plugins.ToStringPlugin"/>
        <!--注释生成器-->
        <commentGenerator>
            <!--是否阻止生成注释-->
            <property name="suppressAllComments" value="true"/>
            <!--是否生成带注释的时间戳-->
            <property name="suppressDate" value="true"/>
            <!--是否添加数据表的备注信息-->
            <property name="addRemarkComments" value="false"/>
        </commentGenerator>
        <!--JDBC数据源连接-->
        <jdbcConnection driverClass="com.mysql.cj.jdbc.Driver"
                        connectionURL="jdbc:mysql://localhost:3306/hc_file_up_down?serverTimezone=UTC"
                        userId="root"
                        password="123456"
        />
        <!--实体类代码生成器-->
        <javaModelGenerator targetPackage="cn.hctech2006.hcuufile.bean" targetProject="src\main\java">
<!--            <property name="trimStrings" value="true"/>-->
        </javaModelGenerator>
        <!--MapperXML文件生成器-->
        <sqlMapGenerator targetPackage="mappers" targetProject="src\main\resources"/>
        <!--Mappper接口生成器-->
        <javaClientGenerator type="XMLMAPPER" targetPackage="cn.hctech2006.hcuufile.mapper" targetProject="src\main\java"/>
        <!--数据库表配置-->
        <table tableName="hc_uu_form_code">
            <!--数据库主键生成策略-->
            <generatedKey column="id" sqlStatement="Mysql"/>
        </table>
    </context>
</generatorConfiguration>